dscamera/__init__.py
dscamera/camera.py
dscamera-0.0.4.dist-info/LICENSE
dscamera-0.0.4.dist-info/METADATA
dscamera-0.0.4.dist-info/WHEEL
dscamera-0.0.4.dist-info/top_level.txt
dscamera-0.0.4.dist-info/RECORD
