Metadata-Version: 2.1
Name: dscamera
Version: 0.0.4
Summary: Python library for Double Sphere Camera Model
Home-page: https://github.com/matsuren/dscamera
Author: Ren Komatsu
Author-email: komatsu@robot.t.u-tokyo.ac.jp
License: MIT License
Platform: UNKNOWN
Classifier: Development Status :: 4 - Beta
Classifier: License :: OSI Approved :: MIT License
Classifier: Programming Language :: Python :: 3
Classifier: Programming Language :: Python :: 3.6
Classifier: Programming Language :: Python :: 3.7
Classifier: Programming Language :: Python :: 3.8
Classifier: Programming Language :: Python :: 3 :: Only
Requires-Python: >=3.6
Requires-Dist: numpy
Requires-Dist: opencv-python
